yagmail/__init__.py
yagmail/__main__.py
yagmail/compat.py
yagmail/dkim.py
yagmail/error.py
yagmail/headers.py
yagmail/log.py
yagmail/message.py
yagmail/oauth2.py
yagmail/password.py
yagmail/sender.py
yagmail/utils.py
yagmail/validate.py
yagmail-0.15.287.dist-info/LICENSE
yagmail-0.15.287.dist-info/METADATA
yagmail-0.15.287.dist-info/WHEEL
yagmail-0.15.287.dist-info/entry_points.txt
yagmail-0.15.287.dist-info/top_level.txt
yagmail-0.15.287.dist-info/RECORD
